py_chartmetric_api/__init__.py
py_chartmetric_api/artist.py
py_chartmetric_api/py_chartmetric_api.py
py_chartmetric_api/utility.py
py_chartmetric_api-0.1.0.dist-info/WHEEL
py_chartmetric_api-0.1.0.dist-info/METADATA
py_chartmetric_api-0.1.0.dist-info/RECORD
