Metadata-Version: 2.1
Name: py-chartmetric-api
Version: 0.1.0
Summary: simple Python library for retrieving data from chartmetric.com
License: MIT
Author: Felix Perron-Brault
Requires-Python: >=3.9,<4.0
Classifier: License :: OSI Approved :: MIT License
Classifier: Programming Language :: Python :: 3
Classifier: Programming Language :: Python :: 3.9
Classifier: Programming Language :: Python :: 3.10
